simple_logging_setup/__init__.py
simple_logging_setup/configuration.py
simple_logging_setup/filter.py
simple_logging_setup/formatter.py
simple_logging_setup/platform.py
simple_logging_setup-0.5.dist-info/LICENSE.txt
simple_logging_setup-0.5.dist-info/METADATA
simple_logging_setup-0.5.dist-info/WHEEL
simple_logging_setup-0.5.dist-info/top_level.txt
simple_logging_setup-0.5.dist-info/RECORD
