Metadata-Version: 2.1
Name: simple-logging-setup
Version: 0.5
Summary: Nice and simple log formatting for the standard library
Author-email: Florian Scherf <mail@florianscherf.de>
License: MIT License
Project-URL: Homepage, https://github.com/fscherf/simple-logging-setup
Project-URL: Repository, https://github.com/fscherf/simple-logging-setup
Project-URL: Bug Tracker, https://github.com/fscherf/simple-logging-setup/issues
Classifier: License :: OSI Approved :: MIT License
License-File: LICENSE.txt
Provides-Extra: dev
Requires-Dist: build ; extra == 'dev'
Requires-Dist: twine ; extra == 'dev'
Requires-Dist: rlpython ; extra == 'dev'
